pykon.py
pykon-0.2.dist-info/METADATA
pykon-0.2.dist-info/WHEEL
pykon-0.2.dist-info/licenses/LICENSE
pykon-0.2.dist-info/RECORD
