Metadata-Version: 2.4
Name: pykon
Version: 0.2
Summary: A module allowing for constant and publicly immutable data.
Project-URL: Repository, https://github.com/sneekyfoxx/Pykon.git
Author-email: Rayshawn Levy <sneekyfoxx09@gmail.com>
Maintainer-email: Rayshawn Levy <sneekyfoxx09@gmail.com>
License-Expression: MIT
License-File: LICENSE
Classifier: Development Status :: 5 - Production/Stable
Classifier: Programming Language :: Python :: 3.12
Classifier: Programming Language :: Python :: 3.13
Classifier: Programming Language :: Python :: 3.14
Requires-Python: >=3.12
